tsipy/__init__.py
tsipy/py.typed
tsipy/version.py
tsipy/correction/__init__.py
tsipy/correction/algorithms.py
tsipy/correction/exposure.py
tsipy/correction/generator.py
tsipy/correction/models.py
tsipy/fusion/__init__.py
tsipy/fusion/core.py
tsipy/fusion/kernels.py
tsipy/fusion/local_gp.py
tsipy/fusion/models_gp.py
tsipy/fusion/utils.py
tsipy/fusion/windows.py
tsipy/utils/__init__.py
tsipy/utils/data.py
tsipy/utils/plot.py
tsipy/utils/print.py
tsipy-1.0.3.dist-info/LICENSE.txt
tsipy-1.0.3.dist-info/METADATA
tsipy-1.0.3.dist-info/WHEEL
tsipy-1.0.3.dist-info/top_level.txt
tsipy-1.0.3.dist-info/RECORD
